[{"total_points":85420,"victories":139,"games_played":232,"kills":1692,"deaths":569,"uuid":"5ed0f7468f7d47df95590521187f6ada","name":"Djouqed","place":500},{"total_points":85255,"victories":148,"games_played":612,"kills":2280,"deaths":2528,"uuid":"6c115781d7944dcd9ac2ea3143e2b351","name":"MiekloBannato","place":501},{"total_points":85180,"victories":209,"games_played":398,"kills":1055,"deaths":1038,"uuid":"497e6237e2bf4d2294b892adb779c4c7","name":"Zhadow_","place":502},{"total_points":85175,"victories":199,"games_played":745,"kills":1029,"deaths":3258,"uuid":"b87153fa9b6445578043cafd4d8f00bd","name":"xBree","place":503},{"total_points":85165,"victories":206,"games_played":408,"kills":1746,"deaths":1227,"uuid":"a21b36710ea84a6082211efdff65e011","name":"HealthySloth","place":504},{"total_points":84810,"victories":224,"games_played":497,"kills":977,"deaths":1029,"uuid":"33b5f222dc004e4bb5d915f7a4c85d75","name":"deema_4up","place":505},{"total_points":84630,"victories":214,"games_played":266,"kills":1319,"deaths":683,"uuid":"6d80ca2d55b94c6b8277927e661760c8","name":"Adept","place":506},{"total_points":84465,"victories":146,"games_played":300,"kills":1739,"deaths":1404,"uuid":"6a263b4e4b5946da956d17cbf5e72010","name":"Jayson55","place":507},{"total_points":84450,"victories":150,"games_played":359,"kills":2608,"deaths":1382,"uuid":"defaa0592d5b4ceabc2cd614cbce5c56","name":"mr_pilot","place":508},{"total_points":84165,"victories":182,"games_played":304,"kills":2072,"deaths":898,"uuid":"79bdaa154f734c7badbef06142a1d8f2","name":"ICqntSpeel","place":509},{"total_points":84085,"victories":108,"games_played":630,"kills":2175,"deaths":1965,"uuid":"2f42911250cc495f82fc308925da9652","name":"TheEpicNinja_MC","place":510},{"total_points":84070,"victories":182,"games_played":669,"kills":1486,"deaths":2733,"uuid":"3b31e52c02f34f8bbe2874c93a8509ff","name":"MichealY","place":511},{"total_points":84030,"victories":148,"games_played":362,"kills":2205,"deaths":1591,"uuid":"84dde01cd80b43e98498c5aabf03daaf","name":"FahadKhaild","place":512},{"total_points":83980,"victories":204,"games_played":500,"kills":1407,"deaths":2761,"uuid":"5ae9cc0dd23d486e96de1deb6c9ef56a","name":"Rigatoni_Donuts","place":513},{"total_points":83890,"victories":184,"games_played":1143,"kills":1191,"deaths":4766,"uuid":"96eef5ebd40649aaad4b8b66ae953370","name":"LegendaryJin","place":514},{"total_points":83885,"victories":135,"games_played":246,"kills":1373,"deaths":709,"uuid":"f17bd3c3020a4065966b71ad4156d8fb","name":"Ilcured","place":515},{"total_points":83710,"victories":184,"games_played":359,"kills":1414,"deaths":1342,"uuid":"d9354928568c45979f15b49a47dd3d68","name":"AminoAcid","place":516},{"total_points":83675,"victories":215,"games_played":806,"kills":1293,"deaths":3959,"uuid":"83d664d902e24ab9b81f40d7617fab4f","name":"RocketStart","place":517},{"total_points":83445,"victories":244,"games_played":408,"kills":929,"deaths":1298,"uuid":"2dee391fcbe548f4b146590776df2a5d","name":"bunnina","place":518},{"total_points":83435,"victories":182,"games_played":271,"kills":1812,"deaths":905,"uuid":"c82560b801994bf28eebe68316317f32","name":"FlowerBoiT","place":519},{"total_points":83395,"victories":196,"games_played":685,"kills":1002,"deaths":3291,"uuid":"80f8fd0617884e23b15442fb44253e63","name":"CircuitCity","place":520},{"total_points":83175,"victories":157,"games_played":391,"kills":2190,"deaths":1589,"uuid":"7d65485a9e9e40299ce65377b8c1b79a","name":"Jongyeon0331","place":521},{"total_points":83110,"victories":195,"games_played":834,"kills":1117,"deaths":3581,"uuid":"cd79932355444db79b9b0253ae0767ce","name":"baldchinesehobo","place":522},{"total_points":82945,"victories":207,"games_played":600,"kills":1078,"deaths":1480,"uuid":"0dfaa59ddd40437bb60c30efa9b2da5d","name":"fatdump","place":523},{"total_points":82915,"victories":235,"games_played":604,"kills":996,"deaths":1626,"uuid":"f1c57ce158074224bc0be45d183d86d8","name":"x_X5SOSfangirlxd","place":524},{"total_points":82890,"victories":152,"games_played":511,"kills":1380,"deaths":1274,"uuid":"7afdf70fd95546b1bbc61a2f422d34b2","name":"TimberWolf2711","place":525},{"total_points":82815,"victories":162,"games_played":338,"kills":1143,"deaths":984,"uuid":"a27f7aeb67ff454bb9ef87d35f61e07a","name":"n2i","place":526},{"total_points":82805,"victories":149,"games_played":669,"kills":1885,"deaths":2606,"uuid":"c65e5e5c8cdc4708929dde9aa4f6ef1a","name":"archangel1957","place":527},{"total_points":82615,"victories":209,"games_played":336,"kills":1284,"deaths":983,"uuid":"0accdec5810d4895acd9493f8683b071","name":"Soupa","place":528},{"total_points":82590,"victories":180,"games_played":896,"kills":1587,"deaths":4277,"uuid":"77cc731d069f4adbb5a3c5cd04f2ae82","name":"Philip1207","place":529},{"total_points":82445,"victories":184,"games_played":236,"kills":1845,"deaths":935,"uuid":"8d5f9174abef4ff3adeca469fcdb164b","name":"IdcCali","place":530},{"total_points":82410,"victories":213,"games_played":264,"kills":819,"deaths":803,"uuid":"f0c9754b10b0498a9a2e567b64d073a2","name":"LordDeWitt","place":531},{"total_points":82325,"victories":189,"games_played":819,"kills":1280,"deaths":3281,"uuid":"6530390619ad4000b1e97d9e8f32d949","name":"xItzSmallpig_cw","place":532},{"total_points":82290,"victories":182,"games_played":489,"kills":1457,"deaths":1534,"uuid":"8d93b3ef8f9e4a468fc345b3130a0b04","name":"MiraculousFox","place":533},{"total_points":82250,"victories":229,"games_played":427,"kills":872,"deaths":1579,"uuid":"66e7de303fa348768bb987709de5f213","name":"frogdreck1","place":534},{"total_points":82220,"victories":145,"games_played":378,"kills":1783,"deaths":1485,"uuid":"8575e004bddb4e9f885ea566c014c964","name":"_HappyCooL_","place":535},{"total_points":82165,"victories":197,"games_played":786,"kills":1048,"deaths":2167,"uuid":"9122c2b54295487299fb85fcee4b1b92","name":"BooniSpooni","place":536},{"total_points":81810,"victories":241,"games_played":271,"kills":949,"deaths":654,"uuid":"629f2895b61842cfa8b47b7cabd738c7","name":"NatiGroce","place":537},{"total_points":81810,"victories":142,"games_played":283,"kills":1993,"deaths":898,"uuid":"f7b7989918c24aaba60d05f272e28cce","name":"ltsquellette","place":538},{"total_points":81675,"victories":128,"games_played":272,"kills":1328,"deaths":709,"uuid":"bca4572809e04f128ef36c30b6b7789d","name":"Astral_Defender","place":539},{"total_points":81470,"victories":204,"games_played":274,"kills":1784,"deaths":1810,"uuid":"d9513c50b94e4eb4990c044892b2d0cf","name":"sade479","place":540},{"total_points":81430,"victories":167,"games_played":626,"kills":1128,"deaths":2770,"uuid":"d35bdbc9dc724d8cb03e199abc0ffb9e","name":"EDragonSlayer","place":541},{"total_points":81350,"victories":179,"games_played":393,"kills":1916,"deaths":1116,"uuid":"a0ce718cf61b4be4a6974ecfea14b067","name":"emilie_mortensen","place":542},{"total_points":81255,"victories":192,"games_played":376,"kills":1369,"deaths":1301,"uuid":"bc2a7bf17e2d455f8be1aabe522d40ca","name":"NepDragon","place":543},{"total_points":80880,"victories":193,"games_played":297,"kills":1451,"deaths":1324,"uuid":"e04524f667d242e7b6db64676ccdb960","name":"Minti","place":544},{"total_points":80755,"victories":219,"games_played":256,"kills":816,"deaths":478,"uuid":"675628898e284729afdb95f2df62b2d2","name":"Shaboodle","place":545},{"total_points":80750,"victories":181,"games_played":876,"kills":1476,"deaths":3663,"uuid":"1fb626bc6d1849bba5f6b68bbef55ac3","name":"Nirio","place":546},{"total_points":80675,"victories":187,"games_played":529,"kills":1688,"deaths":2107,"uuid":"f8909ff8bb0e423aa5466d23294faf33","name":"Katro","place":547},{"total_points":80395,"victories":182,"games_played":611,"kills":1732,"deaths":1678,"uuid":"e0991bde21c547ba82962696a5a1049d","name":"NA_YatogamiTohka","place":548},{"total_points":80250,"victories":231,"games_played":317,"kills":1054,"deaths":1349,"uuid":"af3e6afd2a4a48a3ba03b80d2cfa5134","name":"Jahziyah","place":549},{"total_points":80215,"victories":147,"games_played":489,"kills":1508,"deaths":1379,"uuid":"88274fff421e4702b08d079bb9025ebd","name":"iliketroop1234","place":550},{"total_points":80135,"victories":147,"games_played":489,"kills":1364,"deaths":1612,"uuid":"08d9a87b096b44cfb9e0312c8d9e3c46","name":"Edge_Fur","place":551},{"total_points":79945,"victories":201,"games_played":289,"kills":1415,"deaths":923,"uuid":"731ea64c0fe04ceaa3e2f90fa6e07322","name":"DonaldGlovver","place":552},{"total_points":79785,"victories":163,"games_played":337,"kills":1908,"deaths":1307,"uuid":"8479522d914e47c69dc43703b00e2aa3","name":"Paquetero","place":553},{"total_points":79725,"victories":118,"games_played":619,"kills":2224,"deaths":2786,"uuid":"0d3de87ba0db4ec7bcce3608b62867c9","name":"Sandy_fun","place":554},{"total_points":79630,"victories":163,"games_played":231,"kills":2342,"deaths":336,"uuid":"a334a48dbb3240fe8a9966f7f7bd0d80","name":"OptimusPriime","place":555},{"total_points":79620,"victories":106,"games_played":272,"kills":1773,"deaths":591,"uuid":"0157b43c08484e808a9630a714f84e74","name":"1707hm","place":556},{"total_points":79250,"victories":136,"games_played":595,"kills":2153,"deaths":1921,"uuid":"e05aa311a8f8473ea1161f21a9848915","name":"Anjings","place":557},{"total_points":79135,"victories":194,"games_played":473,"kills":1215,"deaths":2007,"uuid":"7769094d8f874f3296a5860e1555c799","name":"Rapha2402","place":558},{"total_points":79085,"victories":211,"games_played":435,"kills":1493,"deaths":2879,"uuid":"e7cbf5b680e342a381bfb99cee6c2d1a","name":"Chris_G2000","place":559},{"total_points":78940,"victories":132,"games_played":245,"kills":2551,"deaths":872,"uuid":"5db567a3248a4435951b5f190f22cdab","name":"Cris011","place":560},{"total_points":78940,"victories":144,"games_played":384,"kills":2384,"deaths":2548,"uuid":"529bdcca13f84b7fb2f55d3ea5aa4b7c","name":"Conductors","place":561},{"total_points":78930,"victories":169,"games_played":238,"kills":1705,"deaths":408,"uuid":"e98f604039f640c2a3fbe34f0624eeaf","name":"SpArKyxRAIN","place":562},{"total_points":78790,"victories":129,"games_played":528,"kills":2064,"deaths":2792,"uuid":"8552202132de4734a9c79264d81fcd53","name":"MattC_92","place":563},{"total_points":78760,"victories":166,"games_played":289,"kills":2082,"deaths":993,"uuid":"2c229eabaaf342b399ce56e7163d616c","name":"RayMoond","place":564},{"total_points":78655,"victories":190,"games_played":482,"kills":1437,"deaths":1081,"uuid":"9c8324f9ca334a5e847c5b45d83579d4","name":"BaconGOD_","place":565},{"total_points":78565,"victories":220,"games_played":567,"kills":1113,"deaths":1261,"uuid":"2aa938ebc7a949c8876cd96d947fb5d4","name":"Sharebear90","place":566},{"total_points":78545,"victories":143,"games_played":393,"kills":1986,"deaths":1359,"uuid":"f847e8ae0e4647c8bed6e0d43cdfe410","name":"Several_Timezz","place":567},{"total_points":78535,"victories":169,"games_played":509,"kills":1430,"deaths":1735,"uuid":"b322bafc1b0548809adf9c6c9d19e522","name":"Felcanio","place":568},{"total_points":78450,"victories":189,"games_played":590,"kills":1169,"deaths":2426,"uuid":"1369bd6d34e94acd8895fa7c8f8d3a95","name":"Wozlings","place":569},{"total_points":78430,"victories":128,"games_played":459,"kills":1905,"deaths":1889,"uuid":"7ea51237d9f04dd0808ab727a98c7170","name":"Best_Ray","place":570},{"total_points":78245,"victories":232,"games_played":582,"kills":855,"deaths":1001,"uuid":"27dfeb487d5a43dba477db8c6c3d86d2","name":"_ccgamer_","place":571},{"total_points":78030,"victories":154,"games_played":544,"kills":1216,"deaths":1913,"uuid":"2033743a080d43279ec879e09cd08f78","name":"SplayX","place":572},{"total_points":77805,"victories":129,"games_played":489,"kills":2527,"deaths":1303,"uuid":"b2175a14ab6b457988ed3fd6d08d473a","name":"killianOne","place":573},{"total_points":77795,"victories":149,"games_played":224,"kills":1015,"deaths":760,"uuid":"4712e49c1ccc4d2a93c2a9b1be8ca60f","name":"Rosanor","place":574},{"total_points":77605,"victories":160,"games_played":233,"kills":1121,"deaths":848,"uuid":"d87b3a20519e42b1b6d883105ce55a02","name":"ISLW","place":575},{"total_points":77515,"victories":144,"games_played":254,"kills":2054,"deaths":731,"uuid":"724497035e0c4b378975589026e9e31f","name":"CobraZeeer","place":576},{"total_points":77475,"victories":135,"games_played":269,"kills":2125,"deaths":864,"uuid":"1f3bbebaa2c24cbabcadc1d429f39c09","name":"Onuratus","place":577},{"total_points":77470,"victories":124,"games_played":721,"kills":2038,"deaths":2563,"uuid":"efa0736835e2425cad15e5e6d980c472","name":"_CMJ_","place":578},{"total_points":77430,"victories":199,"games_played":647,"kills":1250,"deaths":2011,"uuid":"0634b3dbbf3649f087e9ebea5c26e5a0","name":"_Cynthia","place":579},{"total_points":77345,"victories":103,"games_played":274,"kills":1856,"deaths":1036,"uuid":"7cdcc49d15a4431bb3b685043b4ab642","name":"FastMovinq","place":580},{"total_points":77345,"victories":150,"games_played":565,"kills":1806,"deaths":1956,"uuid":"01a4643ae93c43c2b739c430dc620081","name":"charliebiron","place":581},{"total_points":77340,"victories":168,"games_played":253,"kills":1650,"deaths":907,"uuid":"fdbe88ed58194dcf81a8ce41e46bb1f9","name":"Teennagel","place":582},{"total_points":77130,"victories":115,"games_played":223,"kills":1506,"deaths":728,"uuid":"56f0e9fe8f7b435da6a1aaceaba87c50","name":"Monkerer","place":583},{"total_points":76880,"victories":178,"games_played":356,"kills":1426,"deaths":864,"uuid":"7e51387e045644d7ae78fd30b9f4cf6f","name":"DE_Wertarbeit","place":584},{"total_points":76745,"victories":160,"games_played":199,"kills":1241,"deaths":754,"uuid":"a2409833016a4e368b58348da8cea1a4","name":"DeamonLoL","place":585},{"total_points":76715,"victories":212,"games_played":316,"kills":810,"deaths":519,"uuid":"bfb48e73f3054cc8b802e767a22cd131","name":"Adeerable","place":586},{"total_points":76555,"victories":145,"games_played":287,"kills":1768,"deaths":893,"uuid":"81068d27a9e54f6ea743cf7bfcd8616f","name":"Zebrazix","place":587},{"total_points":76555,"victories":158,"games_played":446,"kills":1326,"deaths":1448,"uuid":"4164d01f09bf471487e2a9d23d716db5","name":"xArcticDemonx","place":588},{"total_points":76410,"victories":157,"games_played":257,"kills":1618,"deaths":1125,"uuid":"a75f647a71be4370976b392ca304a0f0","name":"MashiroUdon","place":589},{"total_points":76240,"victories":122,"games_played":525,"kills":2086,"deaths":2270,"uuid":"d88e7a25392c4d86878e28dbc166af79","name":"Holgon","place":590},{"total_points":75665,"victories":179,"games_played":748,"kills":1314,"deaths":2458,"uuid":"23c23f902849466096cc8b4b67dc1765","name":"Darqui","place":591},{"total_points":75270,"victories":129,"games_played":358,"kills":1101,"deaths":1061,"uuid":"3f6d5753277847c989847e2294d73434","name":"Delial","place":592},{"total_points":75075,"victories":165,"games_played":909,"kills":1394,"deaths":2011,"uuid":"44245d20308b41d590ce4f7c0dbfa234","name":"SwordCraftGaming","place":593},{"total_points":75030,"victories":141,"games_played":475,"kills":2058,"deaths":1669,"uuid":"8d89baa19b7d487bbd1bd6680d1eac72","name":"cheriecool","place":594},{"total_points":74955,"victories":171,"games_played":401,"kills":1334,"deaths":807,"uuid":"4d36b1715ae645a696146a76d5613e24","name":"WhakaMacaroni","place":595},{"total_points":74950,"victories":181,"games_played":741,"kills":1308,"deaths":3221,"uuid":"5ee4a4a289104e55bfab5bdccecc3f01","name":"Alfr","place":596},{"total_points":74910,"victories":218,"games_played":318,"kills":1034,"deaths":823,"uuid":"4fdba1d9014b4aaab6f767cb4cb81fd5","name":"Mystical_CL","place":597},{"total_points":74865,"victories":165,"games_played":363,"kills":902,"deaths":1057,"uuid":"b769cd5ca48344b280d96fb18e62bc5e","name":"Pokemom","place":598},{"total_points":74640,"victories":131,"games_played":288,"kills":1587,"deaths":1193,"uuid":"d7a2f0ee892a40bfadd14966c6c84681","name":"Stevendood","place":599}]
